setup.py
embedchain_albert/__init__.py
embedchain_albert/embedchain.py
embedchain_albert/utils.py
embedchain_albert.egg-info/PKG-INFO
embedchain_albert.egg-info/SOURCES.txt
embedchain_albert.egg-info/dependency_links.txt
embedchain_albert.egg-info/top_level.txt
embedchain_albert/apps/App.py
embedchain_albert/apps/CustomApp.py
embedchain_albert/apps/Llama2App.py
embedchain_albert/apps/OpenSourceApp.py
embedchain_albert/apps/PersonApp.py
embedchain_albert/apps/__init__.py
embedchain_albert/bots/__init__.py
embedchain_albert/bots/base.py
embedchain_albert/bots/whatsapp.py
embedchain_albert/chunkers/__init__.py
embedchain_albert/chunkers/base_chunker.py
embedchain_albert/chunkers/csv.py
embedchain_albert/chunkers/docs_site.py
embedchain_albert/chunkers/docx_file.py
embedchain_albert/chunkers/notion.py
embedchain_albert/chunkers/pdf_file.py
embedchain_albert/chunkers/qna_pair.py
embedchain_albert/chunkers/text.py
embedchain_albert/chunkers/web_page.py
embedchain_albert/chunkers/youtube_video.py
embedchain_albert/config/AddConfig.py
embedchain_albert/config/BaseConfig.py
embedchain_albert/config/ChatConfig.py
embedchain_albert/config/QueryConfig.py
embedchain_albert/config/__init__.py
embedchain_albert/config/apps/AppConfig.py
embedchain_albert/config/apps/BaseAppConfig.py
embedchain_albert/config/apps/CustomAppConfig.py
embedchain_albert/config/apps/OpenSourceAppConfig.py
embedchain_albert/config/apps/__init__.py
embedchain_albert/config/vectordbs/ElasticsearchDBConfig.py
embedchain_albert/config/vectordbs/__init__.py
embedchain_albert/data_formatter/__init__.py
embedchain_albert/data_formatter/data_formatter.py
embedchain_albert/loaders/__init__.py
embedchain_albert/loaders/base_loader.py
embedchain_albert/loaders/csv.py
embedchain_albert/loaders/docs_site_loader.py
embedchain_albert/loaders/docx_file.py
embedchain_albert/loaders/local_qna_pair.py
embedchain_albert/loaders/local_text.py
embedchain_albert/loaders/notion.py
embedchain_albert/loaders/pdf_file.py
embedchain_albert/loaders/sitemap.py
embedchain_albert/loaders/web_page.py
embedchain_albert/loaders/youtube_video.py
embedchain_albert/models/EmbeddingFunctions.py
