Metadata-Version: 2.1
Name: embedchain-albert
Version: 0.1.0
Summary: An example of Python package
Home-page: https://github.com/embedchain/embedchain
Author: Your Name
Author-email: your.email@domain.com
